tokenValidator/Messages.py
tokenValidator/TokenValidator.py
tokenValidator/__init__.py
lb_authorization-1.0.0.dist-info/METADATA
lb_authorization-1.0.0.dist-info/WHEEL
lb_authorization-1.0.0.dist-info/top_level.txt
lb_authorization-1.0.0.dist-info/RECORD
