Metadata-Version: 2.1
Name: lb-authorization
Version: 1.0.0
Summary: Library for control tokens service
Author: Lucas Barros
Author-email: lucasbarros2000@hotmail.com
Classifier: Programming Language :: Python :: 3.6
Classifier: License :: OSI Approved :: MIT License
Classifier: Operating System :: OS Independent
Requires-Python: >=3.6
